
{"name":"SkyRoof Wehsite","items":[{"name":"Download","href":"download.html","topicHref":"download.html"},{"name":"User's Guide","href":"users_guide/overview.html","tocHref":"users_guide/toc.html","topicHref":"users_guide/overview.html"},{"name":"Credits","href":"credits.html","topicHref":"credits.html"},{"name":"Source Code","href":"https://github.com/VE3NEA/SkyRoof","topicHref":"https://github.com/VE3NEA/SkyRoof"}],"pdf":false,"pdfCoverPage":"users_guide/pdf_cover.html","pdfFileName":"skyroof_users_guide.pdf","pdfTocPage":true}
